README
setup.py
tlutil/__init__.py
tlutil/caches.py
tlutil/errors.py
tlutil/factory.py
tlutil/helpers.py
tlutil/json.py
tlutil/middlewares.py
tlutil/rc4.py
tlutil/status.py
tlutil/time.py
tlutil.egg-info/PKG-INFO
tlutil.egg-info/SOURCES.txt
tlutil.egg-info/dependency_links.txt
tlutil.egg-info/not-zip-safe
tlutil.egg-info/requires.txt
tlutil.egg-info/top_level.txt