Metadata-Version: 1.1
Name: tlutil
Version: 0.0.2
Summary: tuoluo tool package
Home-page: http://github.com/zakzou/tlutil
Author: zwczou
Author-email: zwczou@gmail.com
License: BSD
Platform: any
Classifier: Environment :: Web Environment
Classifier: Intended Audience :: Developers
Classifier: License :: OSI Approved :: BSD License
Classifier: Operating System :: OS Independent
Classifier: Programming Language :: Python
Classifier: Framework :: Flask
